turntable/__init__.py
turntable/_version.py
turntable/press.py
turntable/spin.py
turntable/utils.py
turntable-0.2.1.dist-info/DESCRIPTION.rst
turntable-0.2.1.dist-info/METADATA
turntable-0.2.1.dist-info/metadata.json
turntable-0.2.1.dist-info/RECORD
turntable-0.2.1.dist-info/top_level.txt
turntable-0.2.1.dist-info/WHEEL
