Metadata-Version: 2.0
Name: turntable
Version: 0.2.1
Summary: TURNTABLE provides a functional framework for parallel processing DataFrames
Home-page: https://github.com/jshiv/turntable
Author: Jason Shiverick
Author-email: jshiv00@gmail.com
License: MIT
Download-URL: https://github.com/jshiv/turntable
Platform: UNKNOWN
Requires-Dist: pandas
